main.py
mseep_lol_client_mcp-0.1.4.dist-info/licenses/LICENSE
mseep_lol_client_mcp-0.1.4.dist-info/METADATA
mseep_lol_client_mcp-0.1.4.dist-info/WHEEL
mseep_lol_client_mcp-0.1.4.dist-info/entry_points.txt
mseep_lol_client_mcp-0.1.4.dist-info/top_level.txt
mseep_lol_client_mcp-0.1.4.dist-info/RECORD
